MANIFEST.in
setup.py
src/django_webid/__init__.py
src/django_webid/provider/__init__.py
src/django_webid/provider/admin.py
src/django_webid/provider/forms.py
src/django_webid/provider/models.py
src/django_webid/provider/provider_settings.py
src/django_webid/provider/urls.py
src/django_webid/provider/views.py
src/django_webid/provider/webiduri.py
src/django_webid/provider/certs/__init__.py
src/django_webid/provider/certs/utils.py
src/django_webid/provider/management/__init__.py
src/django_webid/provider/management/certconfig_defaults.py
src/django_webid/provider/templates/django_webid/provider/.webid_b64_cert.html.swp
src/django_webid/provider/templates/django_webid/provider/.webid_index.html.swp
src/django_webid/provider/templates/django_webid/provider/base.html
src/django_webid/provider/templates/django_webid/provider/base_site.html
src/django_webid/provider/templates/django_webid/provider/cert_detail.html
src/django_webid/provider/templates/django_webid/provider/cert_list.html
src/django_webid/provider/templates/django_webid/provider/cert_revoke.html
src/django_webid/provider/templates/django_webid/provider/cert_revoked.html
src/django_webid/provider/templates/django_webid/provider/create_user.html
src/django_webid/provider/templates/django_webid/provider/intro.html
src/django_webid/provider/templates/django_webid/provider/login_header.html
src/django_webid/provider/templates/django_webid/provider/site_base.html
src/django_webid/provider/templates/django_webid/provider/webid_add_to_user.html
src/django_webid/provider/templates/django_webid/provider/webid_b64_cert.html
src/django_webid/provider/templates/django_webid/provider/webid_cert_postinst.html
src/django_webid/provider/templates/django_webid/provider/webid_identity.html
src/django_webid/provider/templates/django_webid/provider/webid_identity_keygen.html
src/django_webid/provider/templates/django_webid/provider/webid_index.html
src/django_webid/provider/templates/django_webid/provider/webid_intro.html
src/django_webid_provider.egg-info/PKG-INFO
src/django_webid_provider.egg-info/SOURCES.txt
src/django_webid_provider.egg-info/dependency_links.txt
src/django_webid_provider.egg-info/namespace_packages.txt
src/django_webid_provider.egg-info/not-zip-safe
src/django_webid_provider.egg-info/requires.txt
src/django_webid_provider.egg-info/top_level.txt