Metadata-Version: 1.1
Name: django-webid-provider
Version: 0.2
Summary: A reusable django app that turns any django-powered site into a WebID provider
Home-page: https://github.com/bennomadic/django-webid-provider
Author: Ben Carrillo
Author-email: bennomadic@gmail.com
License: UNKNOWN
Download-URL: https://github.com/bennomadic/django-webid-provider/tarball/v0.2
Keywords: foaf,ssl,webid,x509,certificate,client certificate,authentication,authorization,django
Platform: UNKNOWN
Classifier: Development Status :: 3 - Alpha
Classifier: Environment :: Web Environment
Classifier: Intended Audience :: Developers
Classifier: License :: OSI Approved :: GNU General Public License (GPL)
Classifier: Operating System :: OS Independent
Classifier: Programming Language :: Python
Classifier: Programming Language :: JavaScript
Classifier: Framework :: Django
Classifier: Topic :: Internet :: WWW/HTTP
Classifier: Topic :: Software Development :: Libraries :: Python Modules
Classifier: Topic :: Security :: Cryptography
